fzy/__init__.py
fzy/filtering.py
fzy/py.typed
fzy/tui.py
fzy/util.py
fzy-0.1.0.dist-info/licenses/LICENSE
fzy-0.1.0.dist-info/METADATA
fzy-0.1.0.dist-info/WHEEL
fzy-0.1.0.dist-info/entry_points.txt
fzy-0.1.0.dist-info/top_level.txt
fzy-0.1.0.dist-info/RECORD
