Metadata-Version: 2.4
Name: fzy
Version: 0.1.0
Summary: A tool which interactively displays YAML files and provides fuzzy interactive searching and filtering.
License-File: LICENSE
Requires-Dist: urwid>=2.5.0
Requires-Dist: pygments
Requires-Dist: pyyaml
Dynamic: license-file
